ovos_PHAL_plugin_commonIOT/__init__.py
ovos_PHAL_plugin_commonIOT/device_manager.py
ovos_PHAL_plugin_commonIOT/service.py
ovos_PHAL_plugin_commonIOT/version.py
ovos_PHAL_plugin_commonIOT/vui.py
ovos_PHAL_plugin_commonIOT/locale/en-us/dialogs/device.not.found.dialog
ovos_PHAL_plugin_commonIOT/locale/en-us/dialogs/lights.action.not.available.dialog
ovos_PHAL_plugin_commonIOT/locale/en-us/dialogs/lights.current.brightness.dialog
ovos_PHAL_plugin_commonIOT/locale/en-us/dialogs/lights.current.color.dialog
ovos_PHAL_plugin_commonIOT/locale/en-us/dialogs/lights.status.not.available.dialog
ovos_PHAL_plugin_commonIOT/locale/en-us/dialogs/no_area.dialog
ovos_PHAL_plugin_commonIOT/locale/en-us/dialogs/no_device_class.dialog
ovos_PHAL_plugin_commonIOT/locale/en-us/dialogs/no_entity.dialog
ovos_PHAL_plugin_commonIOT/locale/en-us/entities/color.entity
ovos_PHAL_plugin_commonIOT/locale/en-us/intents/lights.decrease.brightness.intent
ovos_PHAL_plugin_commonIOT/locale/en-us/intents/lights.get.brightness.intent
ovos_PHAL_plugin_commonIOT/locale/en-us/intents/lights.get.color.intent
ovos_PHAL_plugin_commonIOT/locale/en-us/intents/lights.increase.brightness.intent
ovos_PHAL_plugin_commonIOT/locale/en-us/intents/lights.set.brightness.intent
ovos_PHAL_plugin_commonIOT/locale/en-us/intents/lights.set.color.intent
ovos_PHAL_plugin_commonIOT/locale/en-us/intents/mediaplayer.get.volume.intent
ovos_PHAL_plugin_commonIOT/locale/en-us/intents/mediaplayer.mute.intent
ovos_PHAL_plugin_commonIOT/locale/en-us/intents/mediaplayer.set.volume.intent
ovos_PHAL_plugin_commonIOT/locale/en-us/intents/mediaplayer.unmute.intent
ovos_PHAL_plugin_commonIOT/locale/en-us/intents/mediaplayer.volume.down.intent
ovos_PHAL_plugin_commonIOT/locale/en-us/intents/mediaplayer.volume.up.intent
ovos_PHAL_plugin_commonIOT/locale/en-us/intents/reboot.intent
ovos_PHAL_plugin_commonIOT/locale/en-us/intents/sleep.intent
ovos_PHAL_plugin_commonIOT/locale/en-us/intents/turn.off.intent
ovos_PHAL_plugin_commonIOT-0.0.0a6.dist-info/METADATA
ovos_PHAL_plugin_commonIOT-0.0.0a6.dist-info/WHEEL
ovos_PHAL_plugin_commonIOT-0.0.0a6.dist-info/entry_points.txt
ovos_PHAL_plugin_commonIOT-0.0.0a6.dist-info/top_level.txt
ovos_PHAL_plugin_commonIOT-0.0.0a6.dist-info/zip-safe
ovos_PHAL_plugin_commonIOT-0.0.0a6.dist-info/RECORD
